tests/__init__.py
tests/test_analyze_utils.py
tests/test_api.py
tests/test_corrector_trainer.py
tests/test_inversion_trainer.py
tests/test_inversion_trainer_bow.py
tests/test_inversion_trainer_na.py
tests/test_models.py
tests/test_models_hf_hub.py
tests/test_sequence_level_beam_generation.py
vec2text/__init__.py
vec2text/aliases.py
vec2text/analyze_utils.py
vec2text/api.py
vec2text/collator.py
vec2text/data_helpers.py
vec2text/experiments.py
vec2text/generation_experiments.py
vec2text/metrics.py
vec2text/precompute_train_hypotheses.py
vec2text/prompts.py
vec2text/run.py
vec2text/run_args.py
vec2text/tokenize_data.py
vec2text/models/__init__.py
vec2text/models/config.py
vec2text/models/corrector_encoder.py
vec2text/models/corrector_encoder_from_logits.py
vec2text/models/inversion.py
vec2text/models/inversion_bow.py
vec2text/models/inversion_decoder.py
vec2text/models/inversion_from_logits.py
vec2text/models/inversion_from_logits_emb.py
vec2text/models/inversion_na.py
vec2text/models/model_utils.py
vec2text/trainers/__init__.py
vec2text/trainers/base.py
vec2text/trainers/corrector.py
vec2text/trainers/inversion.py
vec2text/trainers/inversion_bow.py
vec2text/trainers/inversion_from_logits.py
vec2text/trainers/inversion_na.py
vec2text/trainers_baseline/__init__.py
vec2text/trainers_baseline/decode_inversion_trainer.py
vec2text/trainers_baseline/fewshot_inversion_trainer.py
vec2text/trainers_baseline/jailbreak_prompt_trainer.py
vec2text/utils/__init__.py
vec2text/utils/utils.py
vec2text-0.0.12.dist-info/LICENSE
vec2text-0.0.12.dist-info/METADATA
vec2text-0.0.12.dist-info/WHEEL
vec2text-0.0.12.dist-info/top_level.txt
vec2text-0.0.12.dist-info/RECORD
