Metadata-Version: 2.1
Name: vec2text
Version: 0.0.12
Summary: convert embedding vectors back to text
Author: Jack Morris
Author-email: jxm3@cornell.edu
License-File: LICENSE
Requires-Dist: accelerate
Requires-Dist: bert-score
Requires-Dist: datasets
Requires-Dist: einops
Requires-Dist: evaluate
Requires-Dist: openai
Requires-Dist: optimum
Requires-Dist: pre-commit
Requires-Dist: pylcs
Requires-Dist: rouge-score
Requires-Dist: sacrebleu
Requires-Dist: sentence-transformers
Requires-Dist: tenacity
Requires-Dist: tokenizers
Requires-Dist: tqdm
Requires-Dist: transformers
